[
  {
    "条件": ["f(x) = \\begin{cases} -0.1x^2 + 2.6x + 43 & (0 < x \\\\le 10) \\\\ 59 & (10 < x \\\\le 16) \\\\-3x + 107 & (16 < x \\\\le 30) \\end{cases}"],
    "知识点": "分段函数的最大值可以通过分别计算每个区间内的最大值来确定，然后比较这些最大值找出整体的最大值。",
    "过程": "对于第一段函数-0.1x^2 + 2.6x + 43，在(0, 10]内求最大值。该函数为开口向下的抛物线，其顶点坐标由公式x=-b/2a给出，其中a=-0.1, b=2.6。因此，x_max = -2.6/(2*(-0.1)) = 13，但此值不在给定区间内，故在边界点检查：f(0)=43, f(10)=-0.1*10^2+2.6*10+43=59。"
  },
  {
    "条件": ["f(x) = \\begin{cases} -0.1x^2 + 2.6x + 43 & (0 < x \\\\le 10) \\\\ 59 & (10 < x \\\\le 16) \\\\-3x + 107 & (16 < x \\\\le 30) \\end{cases}"],
    "知识点": "当考虑分段函数的特定区间时，如果该区间定义了一个常数值，则该区间上的函数值保持不变。",
    "过程": "对于第二段[10, 16]，f(x)恒等于59，这意味着在此期间学生的接受能力维持在59这一水平。"
  },
  {
    "条件": ["f(x) = \\begin{cases} -0.1x^2 + 2.6x + 43 & (0 < x \\\\le 10) \\\\ 59 & (10 < x \\\\le 16) \\\\-3x + 107 & (16 < x \\\\le 30) \\end{cases}"],
    "知识点": "线性函数在其定义域内的最大值或最小值通常出现在端点处。",
    "过程": "第三段函数-3x + 107是一个递减直线，因此在(16, 30]内，f(x)的最大值发生在x=16时，即f(16)=-3*16+107=59。"
  },
  {
    "条件": ["f(x) = \\begin{cases} -0.1x^2 + 2.6x + 43 & (0 < x \\\\le 10) \\\\ 59 & (10 < x \\\\le 16) \\\\-3x + 107 & (16 < x \\\\le 30) \\end{cases}"],
    "知识点": "通过比较各段函数的最大值，可以确定整个定义域上函数的最大值及其对应的x值。",
    "过程": "根据上述分析，f(x)的最大值为59，它既出现在x=10时也出现在[10, 16]区间内以及x=16时。因此，学生的接受能力最强的时间是从第10分钟开始一直持续到第16分钟结束，共维持了6分钟。"
  },
  {
    "条件": ["f(x) = \\begin{cases} -0.1x^2 + 2.6x + 43 & (0 < x \\\\le 10) \\\\ 59 & (10 < x \\\\le 16) \\\\-3x + 107 & (16 < x \\\\le 30) \\end{cases}"],
    "知识点": "为了比较不同时间点的学生接受能力，需要将具体的时间值代入相应的函数表达式中进行计算。",
    "过程": "开讲5分钟后，使用第一段函数计算得到f(5)=-0.1*5^2+2.6*5+43=53.5；开讲20分钟后，使用第三段函数计算得f(20)=-3*20+107=47。由此可见，开讲5分钟时学生的接受能力强于开讲20分钟时。"
  }
]